skilllite/__init__.py
skilllite/analyzer.py
skilllite/builtin_tools.py
skilllite/quick.py
skilllite/validation.py
skilllite/cli/__init__.py
skilllite/cli/__main__.py
skilllite/cli/binary.py
skilllite/cli/main.py
skilllite/cli/mcp.py
skilllite/cli/integrations/__init__.py
skilllite/cli/integrations/opencode.py
skilllite/core/__init__.py
skilllite/core/executor.py
skilllite/core/handler.py
skilllite/core/loops.py
skilllite/core/manager.py
skilllite/core/metadata.py
skilllite/core/prompt_builder.py
skilllite/core/registry.py
skilllite/core/skill_info.py
skilllite/core/tool_builder.py
skilllite/core/tools.py
skilllite/mcp/__init__.py
skilllite/mcp/server.py
skilllite/sandbox/__init__.py
skilllite/sandbox/base.py
skilllite/sandbox/config.py
skilllite/sandbox/utils.py
skilllite/sandbox/skillbox/__init__.py
skilllite/sandbox/skillbox/binary.py
skilllite/sandbox/skillbox/executor.py
skilllite-0.1.1.dist-info/licenses/LICENSE
skilllite-0.1.1.dist-info/METADATA
skilllite-0.1.1.dist-info/WHEEL
skilllite-0.1.1.dist-info/entry_points.txt
skilllite-0.1.1.dist-info/top_level.txt
skilllite-0.1.1.dist-info/RECORD
