Metadata-Version: 2.4
Name: skilllite
Version: 0.1.1
Summary: A lightweight Skills execution engine with LLM integration for LLM agents
Author-email: SkillLite Team <skilllite@example.com>
License: MIT
Project-URL: Homepage, https://github.com/EXboys/skilllite
Project-URL: Documentation, https://github.com/EXboys/skilllite#readme
Project-URL: Repository, https://github.com/EXboys/skilllite
Project-URL: Issues, https://github.com/EXboys/skilllite/issues
Keywords: agent,skills,llm,claude,openai,sandbox,tools
Classifier: Development Status :: 3 - Alpha
Classifier: Intended Audience :: Developers
Classifier: License :: OSI Approved :: MIT License
Classifier: Operating System :: MacOS
Classifier: Operating System :: POSIX :: Linux
Classifier: Programming Language :: Python :: 3
Classifier: Programming Language :: Python :: 3.8
Classifier: Programming Language :: Python :: 3.9
Classifier: Programming Language :: Python :: 3.10
Classifier: Programming Language :: Python :: 3.11
Classifier: Programming Language :: Python :: 3.12
Classifier: Topic :: Software Development :: Libraries :: Python Modules
Classifier: Topic :: Scientific/Engineering :: Artificial Intelligence
Requires-Python: >=3.8
License-File: LICENSE
Requires-Dist: pyyaml>=6.0
Provides-Extra: openai
Requires-Dist: openai>=1.0.0; extra == "openai"
Provides-Extra: anthropic
Requires-Dist: anthropic>=0.18.0; extra == "anthropic"
Provides-Extra: mcp
Requires-Dist: mcp>=1.0.0; extra == "mcp"
Provides-Extra: all
Requires-Dist: openai>=1.0.0; extra == "all"
Requires-Dist: anthropic>=0.18.0; extra == "all"
Requires-Dist: mcp>=1.0.0; extra == "all"
Provides-Extra: dev
Requires-Dist: pytest>=7.0; extra == "dev"
Requires-Dist: pytest-asyncio>=0.21.0; extra == "dev"
Requires-Dist: black>=23.0; extra == "dev"
Requires-Dist: mypy>=1.0; extra == "dev"
Requires-Dist: ruff>=0.1.0; extra == "dev"
Dynamic: license-file
